dfcosmic/__init__.py
dfcosmic/core.py
dfcosmic/utils.py
dfcosmic-0.0.1.dist-info/licenses/LICENSE
dfcosmic-0.0.1.dist-info/METADATA
dfcosmic-0.0.1.dist-info/WHEEL
dfcosmic-0.0.1.dist-info/top_level.txt
dfcosmic-0.0.1.dist-info/RECORD
