Metadata-Version: 2.4
Name: dfcosmic
Version: 0.0.1
Summary: A high-performance Python package for cosmic ray removal following the original paper by van Dokkum 2001.
Author-email: Carter Rhea <carter.rhea@dragonfly1000.com>, Steven Janssens <steven.janssens@dragonfly1000.com>, Pieter van Dokkum <pieter.vandokkum@dragonfly1000.com>, Imad Pasha <imad.pasha@dragonfly1000.com>, Roberto Abraham <roberto.abraham@dragonfly1000.com>, "William P. Bowman" <william.bowman@dragonfly1000.com>, Deborah Lokhorst <deborah.lokhorst@dragonfly1000.com>, Seery Chen <seery.chen@dragonfly1000.com>
Project-URL: Homepage, https://github.com/DragonflyTelescope/dfcosmic
Project-URL: Issues, https://github.com/DragonflyTelescope/dfcosmic/issues
Classifier: Development Status :: 3 - Alpha
Classifier: Intended Audience :: Science/Research
Classifier: Topic :: Scientific/Engineering :: Astronomy
Classifier: Programming Language :: Python :: 3
Classifier: Operating System :: OS Independent
Requires-Python: >=3.10
License-File: LICENSE
Requires-Dist: numpy>=1.17.0
Requires-Dist: torch>=1.9.0
Requires-Dist: matplotlib>=3.10.7
Requires-Dist: cmcrameri>=1.9
Provides-Extra: docs
Requires-Dist: sphinx>=5.0.0; extra == "docs"
Requires-Dist: sphinx-autoapi>=2.0.0; extra == "docs"
Requires-Dist: nbsphinx>=0.8.9; extra == "docs"
Requires-Dist: ipykernel>=6.0.0; extra == "docs"
Requires-Dist: sphinx-copybutton==0.5.2; extra == "docs"
Requires-Dist: sphinx-nefertiti==0.8.10; extra == "docs"
Dynamic: license-file
